{"maxLinkValue": 139096, "nodes": [{"event": "homepage new", "value": 139096}, {"event": "Viewed login page", "value": 28019}, {"event": "Viewed report", "value": 13614}, {"event": "Tutorial Shown", "value": 13194}, {"event": "Tutorial Video Started", "value": 7769}, {"event": "Tutorial Video Finished", "value": 1301}, {"event": "clicked logout link", "value": 985}], "maxNodeValue": 139096, "links": [{"source": 0, "target": 1, "value": 28019}, {"source": 1, "target": 2, "value": 13614}, {"source": 2, "target": 3, "value": 4311}, {"source": 3, "target": 4, "value": 148}, {"source": 4, "target": 5, "value": 32}, {"source": 5, "target": 6, "value": 1}, {"source": 0, "target": 3, "value": 1673}, {"source": 4, "target": 6, "value": 4}, {"source": 3, "target": 6, "value": 1}, {"source": 0, "target": 2, "value": 2445}, {"source": 2, "target": 6, "value": 99}, {"source": 0, "target": 6, "value": 985}, {"source": 2, "target": 4, "value": 268}, {"source": 0, "target": 4, "value": 978}]}